fave_asr/__init__.py
fave_asr/fave_asr.py
fave_asr-0.1.0.dist-info/LICENSE
fave_asr-0.1.0.dist-info/METADATA
fave_asr-0.1.0.dist-info/WHEEL
fave_asr-0.1.0.dist-info/RECORD
