Metadata-Version: 2.1
Name: fave-asr
Version: 0.1.0
Summary: Automated transcription and diarization of linguistic data
Home-page: https://forced-alignment-and-vowel-extraction.github.io/fave-asr/
License: GPL-3.0-or-later
Author: Christian Brickhouse
Author-email: brickhouse@stanford.edu
Maintainer: Christian Brickhouse
Maintainer-email: brickhouse@stanford.edu
Requires-Python: >=3.10,<4.0
Classifier: License :: OSI Approved :: GNU General Public License v3 or later (GPLv3+)
Classifier: Programming Language :: Python :: 3
Classifier: Programming Language :: Python :: 3.10
Classifier: Programming Language :: Python :: 3.11
Requires-Dist: GPUtil (>=1.4.0,<2.0.0)
Requires-Dist: TextGrid (>=1.6.1,<2.0.0)
Requires-Dist: psutil (>=5.9.8,<6.0.0)
Requires-Dist: whisper-timestamped (>=1.15.3,<2.0.0)
Requires-Dist: whisperx (>=3.1.2,<4.0.0)
Project-URL: Repository, https://github.com/Forced-Alignment-and-Vowel-Extraction/fave-asr
